iiitb_gc.v
`timescale 1ns / 1ps
//////////////////////////////////////////////////////////////////////////////////
// Company: 
// Engineer: 
// 
// Create Date: 24.07.2022 14:54:14
// Design Name: 
// Module Name: iiitb_gc
// Project Name: 
// Target Devices: 
// Tool Versions: 
// Description: 
// 
// Dependencies: 
// 
// Revision:
// Revision 0.01 - File Created
// Additional Comments:
// 
//////////////////////////////////////////////////////////////////////////////////

// Gray counter

module iiitb_gc
(
	input clk, enable, reset,
	output reg [7:0] gray_count
);

	reg q [8:0];
	reg no_ones_below [7:0];
	reg q_msb;
	
	integer i, j, k;
	
	always @ (posedge clk)
	begin
		if (reset)
		begin
		
			q[0] <= 1;
			for (i = 1; i <= 8; i = i + 1)
				q[i] <= 0;
				
		end
		else if (enable)
		begin
			q[0] <= ~q[0];
			
			for (i = 1; i < 8; i = i + 1)
			begin
				
				q[i] <= q[i] ^ (q[i-1] & no_ones_below[i-1]);
			
			end
			
			q[8] <= q[8] ^ (q_msb & no_ones_below[7]);
		end
	end
	
	
	always @(*)
	begin
		no_ones_below[0] = 1;
		
		for (j = 1; j < 8; j = j + 1)
			no_ones_below[j] = no_ones_below[j-1] & ~q[j-1];
			
		q_msb = q[8] | q[7];
		for (k = 0; k < 8; k = k + 1)
			gray_count[k] = q[k+1];
		end	
		
endmodule

iiitb_gc_tb.v
`timescale 1ns / 1ps
//////////////////////////////////////////////////////////////////////////////////
// Company: 
// Engineer: 
// 
// Create Date: 24.07.2022 16:21:35
// Design Name: 
// Module Name: iiitb_gc_tb
// Project Name: 
// Target Devices: 
// Tool Versions: 
// Description: 
// 
// Dependencies: 
// 
// Revision:
// Revision 0.01 - File Created
// Additional Comments:
// 
//////////////////////////////////////////////////////////////////////////////////


module iiitb_gc_tb();
    reg clk, enable, reset;
    wire [7:0] gray_count;
    
    iiitb_gc gc1(clk, enable, reset, gray_count);
    
    initial
    begin
        clk = 0;
        reset = 1;
        enable = 1;
        
        #5 reset = 0;
        #4000 $finish;     
    end 
    
    always #2 clk = ~clk;
       
endmodule

iiitb_gc.vcd
$date
	Wed Jul 27 15:47:02 2022
$end
$version
	Icarus Verilog
$end
$timescale
	1ps
$end
$scope module iiitb_gc_tb $end
$var wire 8 ! gray_count [7:0] $end
$var reg 1 " clk $end
$var reg 1 # enable $end
$var reg 1 $ reset $end
$scope module gc1 $end
$var wire 1 " clk $end
$var wire 1 # enable $end
$var wire 1 $ reset $end
$var reg 8 % gray_count [7:0] $end
$var reg 1 & q_msb $end
$var integer 32 ' i [31:0] $end
$var integer 32 ( j [31:0] $end
$var integer 32 ) k [31:0] $end
$upscope $end
$upscope $end
$enddefinitions $end
#0
$dumpvars
bx )
bx (
bx '
x&
bx %
1$
1#
0"
bx !
$end
#2000
b0 !
b0 %
b1000 )
0&
b1000 (
b1001 '
1"
#4000
0"
#5000
0$
#6000
b1 !
b1 %
b1000 )
b1000 (
b1000 '
1"
#8000
0"
#10000
b11 !
b11 %
b1000 )
b1000 (
b1000 '
1"
#12000
0"
#14000
b10 !
b10 %
b1000 )
b1000 (
b1000 '
1"
#16000
0"
#18000
b110 !
b110 %
b1000 )
b1000 (
b1000 '
1"
#20000
0"
#22000
b111 !
b111 %
b1000 )
b1000 (
b1000 '
1"
#24000
0"
#26000
b101 !
b101 %
b1000 )
b1000 (
b1000 '
1"
#28000
0"
#30000
b100 !
b100 %
b1000 )
b1000 (
b1000 '
1"
#32000
0"
#34000
b1100 !
b1100 %
b1000 )
b1000 (
b1000 '
1"
#36000
0"
#38000
b1101 !
b1101 %
b1000 )
b1000 (
b1000 '
1"
#40000
0"
#42000
b1111 !
b1111 %
b1000 )
b1000 (
b1000 '
1"
#44000
0"
#46000
b1110 !
b1110 %
b1000 )
b1000 (
b1000 '
1"
#48000
0"
#50000
b1010 !
b1010 %
b1000 )
b1000 (
b1000 '
1"
#52000
0"
#54000
b1011 !
b1011 %
b1000 )
b1000 (
b1000 '
1"
#56000
0"
#58000
b1001 !
b1001 %
b1000 )
b1000 (
b1000 '
1"
#60000
0"
#62000
b1000 !
b1000 %
b1000 )
b1000 (
b1000 '
1"
#64000
0"
#66000
b11000 !
b11000 %
b1000 )
b1000 (
b1000 '
1"
#68000
0"
#70000
b11001 !
b11001 %
b1000 )
b1000 (
b1000 '
1"
#72000
0"
#74000
b11011 !
b11011 %
b1000 )
b1000 (
b1000 '
1"
#76000
0"
#78000
b11010 !
b11010 %
b1000 )
b1000 (
b1000 '
1"
#80000
0"
#82000
b11110 !
b11110 %
b1000 )
b1000 (
b1000 '
1"
#84000
0"
#86000
b11111 !
b11111 %
b1000 )
b1000 (
b1000 '
1"
#88000
0"
#90000
b11101 !
b11101 %
b1000 )
b1000 (
b1000 '
1"
#92000
0"
#94000
b11100 !
b11100 %
b1000 )
b1000 (
b1000 '
1"
#96000
0"
#98000
b10100 !
b10100 %
b1000 )
b1000 (
b1000 '
1"
#100000
0"
#102000
b10101 !
b10101 %
b1000 )
b1000 (
b1000 '
1"
#104000
0"
#106000
b10111 !
b10111 %
b1000 )
b1000 (
b1000 '
1"
#108000
0"
#110000
b10110 !
b10110 %
b1000 )
b1000 (
b1000 '
1"
#112000
0"
#114000
b10010 !
b10010 %
b1000 )
b1000 (
b1000 '
1"
#116000
0"
#118000
b10011 !
b10011 %
b1000 )
b1000 (
b1000 '
1"
#120000
0"
#122000
b10001 !
b10001 %
b1000 )
b1000 (
b1000 '
1"
#124000
0"
#126000
b10000 !
b10000 %
b1000 )
b1000 (
b1000 '
1"
#128000
0"
#130000
b110000 !
b110000 %
b1000 )
b1000 (
b1000 '
1"
#132000
0"
#134000
b110001 !
b110001 %
b1000 )
b1000 (
b1000 '
1"
#136000
0"
#138000
b110011 !
b110011 %
b1000 )
b1000 (
b1000 '
1"
#140000
0"
#142000
b110010 !
b110010 %
b1000 )
b1000 (
b1000 '
1"
#144000
0"
#146000
b110110 !
b110110 %
b1000 )
b1000 (
b1000 '
1"
#148000
0"
#150000
b110111 !
b110111 %
b1000 )
b1000 (
b1000 '
1"
#152000
0"
#154000
b110101 !
b110101 %
b1000 )
b1000 (
b1000 '
1"
#156000
0"
#158000
b110100 !
b110100 %
b1000 )
b1000 (
b1000 '
1"
#160000
0"
#162000
b111100 !
b111100 %
b1000 )
b1000 (
b1000 '
1"
#164000
0"
#166000
b111101 !
b111101 %
b1000 )
b1000 (
b1000 '
1"
#168000
0"
#170000
b111111 !
b111111 %
b1000 )
b1000 (
b1000 '
1"
#172000
0"
#174000
b111110 !
b111110 %
b1000 )
b1000 (
b1000 '
1"
#176000
0"
#178000
b111010 !
b111010 %
b1000 )
b1000 (
b1000 '
1"
#180000
0"
#182000
b111011 !
b111011 %
b1000 )
b1000 (
b1000 '
1"
#184000
0"
#186000
b111001 !
b111001 %
b1000 )
b1000 (
b1000 '
1"
#188000
0"
#190000
b111000 !
b111000 %
b1000 )
b1000 (
b1000 '
1"
#192000
0"
#194000
b101000 !
b101000 %
b1000 )
b1000 (
b1000 '
1"
#196000
0"
#198000
b101001 !
b101001 %
b1000 )
b1000 (
b1000 '
1"
#200000
0"
#202000
b101011 !
b101011 %
b1000 )
b1000 (
b1000 '
1"
#204000
0"
#206000
b101010 !
b101010 %
b1000 )
b1000 (
b1000 '
1"
#208000
0"
#210000
b101110 !
b101110 %
b1000 )
b1000 (
b1000 '
1"
#212000
0"
#214000
b101111 !
b101111 %
b1000 )
b1000 (
b1000 '
1"
#216000
0"
#218000
b101101 !
b101101 %
b1000 )
b1000 (
b1000 '
1"
#220000
0"
#222000
b101100 !
b101100 %
b1000 )
b1000 (
b1000 '
1"
#224000
0"
#226000
b100100 !
b100100 %
b1000 )
b1000 (
b1000 '
1"
#228000
0"
#230000
b100101 !
b100101 %
b1000 )
b1000 (
b1000 '
1"
#232000
0"
#234000
b100111 !
b100111 %
b1000 )
b1000 (
b1000 '
1"
#236000
0"
#238000
b100110 !
b100110 %
b1000 )
b1000 (
b1000 '
1"
#240000
0"
#242000
b100010 !
b100010 %
b1000 )
b1000 (
b1000 '
1"
#244000
0"
#246000
b100011 !
b100011 %
b1000 )
b1000 (
b1000 '
1"
#248000
0"
#250000
b100001 !
b100001 %
b1000 )
b1000 (
b1000 '
1"
#252000
0"
#254000
b100000 !
b100000 %
b1000 )
b1000 (
b1000 '
1"
#256000
0"
#258000
b1100000 !
b1100000 %
b1000 )
1&
b1000 (
b1000 '
1"
#260000
0"
#262000
b1100001 !
b1100001 %
b1000 )
b1000 (
b1000 '
1"
#264000
0"
#266000
b1100011 !
b1100011 %
b1000 )
b1000 (
b1000 '
1"
#268000
0"
#270000
b1100010 !
b1100010 %
b1000 )
b1000 (
b1000 '
1"
#272000
0"
#274000
b1100110 !
b1100110 %
b1000 )
b1000 (
b1000 '
1"
#276000
0"
#278000
b1100111 !
b1100111 %
b1000 )
b1000 (
b1000 '
1"
#280000
0"
#282000
b1100101 !
b1100101 %
b1000 )
b1000 (
b1000 '
1"
#284000
0"
#286000
b1100100 !
b1100100 %
b1000 )
b1000 (
b1000 '
1"
#288000
0"
#290000
b1101100 !
b1101100 %
b1000 )
b1000 (
b1000 '
1"
#292000
0"
#294000
b1101101 !
b1101101 %
b1000 )
b1000 (
b1000 '
1"
#296000
0"
#298000
b1101111 !
b1101111 %
b1000 )
b1000 (
b1000 '
1"
#300000
0"
#302000
b1101110 !
b1101110 %
b1000 )
b1000 (
b1000 '
1"
#304000
0"
#306000
b1101010 !
b1101010 %
b1000 )
b1000 (
b1000 '
1"
#308000
0"
#310000
b1101011 !
b1101011 %
b1000 )
b1000 (
b1000 '
1"
#312000
0"
#314000
b1101001 !
b1101001 %
b1000 )
b1000 (
b1000 '
1"
#316000
0"
#318000
b1101000 !
b1101000 %
b1000 )
b1000 (
b1000 '
1"
#320000
0"
#322000
b1111000 !
b1111000 %
b1000 )
b1000 (
b1000 '
1"
#324000
0"
#326000
b1111001 !
b1111001 %
b1000 )
b1000 (
b1000 '
1"
#328000
0"
#330000
b1111011 !
b1111011 %
b1000 )
b1000 (
b1000 '
1"
#332000
0"
#334000
b1111010 !
b1111010 %
b1000 )
b1000 (
b1000 '
1"
#336000
0"
#338000
b1111110 !
b1111110 %
b1000 )
b1000 (
b1000 '
1"
#340000
0"
#342000
b1111111 !
b1111111 %
b1000 )
b1000 (
b1000 '
1"
#344000
0"
#346000
b1111101 !
b1111101 %
b1000 )
b1000 (
b1000 '
1"
#348000
0"
#350000
b1111100 !
b1111100 %
b1000 )
b1000 (
b1000 '
1"
#352000
0"
#354000
b1110100 !
b1110100 %
b1000 )
b1000 (
b1000 '
1"
#356000
0"
#358000
b1110101 !
b1110101 %
b1000 )
b1000 (
b1000 '
1"
#360000
0"
#362000
b1110111 !
b1110111 %
b1000 )
b1000 (
b1000 '
1"
#364000
0"
#366000
b1110110 !
b1110110 %
b1000 )
b1000 (
b1000 '
1"
#368000
0"
#370000
b1110010 !
b1110010 %
b1000 )
b1000 (
b1000 '
1"
#372000
0"
#374000
b1110011 !
b1110011 %
b1000 )
b1000 (
b1000 '
1"
#376000
0"
#378000
b1110001 !
b1110001 %
b1000 )
b1000 (
b1000 '
1"
#380000
0"
#382000
b1110000 !
b1110000 %
b1000 )
b1000 (
b1000 '
1"
#384000
0"
#386000
b1010000 !
b1010000 %
b1000 )
b1000 (
b1000 '
1"
#388000
0"
#390000
b1010001 !
b1010001 %
b1000 )
b1000 (
b1000 '
1"
#392000
0"
#394000
b1010011 !
b1010011 %
b1000 )
b1000 (
b1000 '
1"
#396000
0"
#398000
b1010010 !
b1010010 %
b1000 )
b1000 (
b1000 '
1"
#400000
0"
#402000
b1010110 !
b1010110 %
b1000 )
b1000 (
b1000 '
1"
#404000
0"
#406000
b1010111 !
b1010111 %
b1000 )
b1000 (
b1000 '
1"
#408000
0"
#410000
b1010101 !
b1010101 %
b1000 )
b1000 (
b1000 '
1"
#412000
0"
#414000
b1010100 !
b1010100 %
b1000 )
b1000 (
b1000 '
1"
#416000
0"
#418000
b1011100 !
b1011100 %
b1000 )
b1000 (
b1000 '
1"
#420000
0"
#422000
b1011101 !
b1011101 %
b1000 )
b1000 (
b1000 '
1"
#424000
0"
#426000
b1011111 !
b1011111 %
b1000 )
b1000 (
b1000 '
1"
#428000
0"
#430000
b1011110 !
b1011110 %
b1000 )
b1000 (
b1000 '
1"
#432000
0"
#434000
b1011010 !
b1011010 %
b1000 )
b1000 (
b1000 '
1"
#436000
0"
#438000
b1011011 !
b1011011 %
b1000 )
b1000 (
b1000 '
1"
#440000
0"
#442000
b1011001 !
b1011001 %
b1000 )
b1000 (
b1000 '
1"
#444000
0"
#446000
b1011000 !
b1011000 %
b1000 )
b1000 (
b1000 '
1"
#448000
0"
#450000
b1001000 !
b1001000 %
b1000 )
b1000 (
b1000 '
1"
#452000
0"
#454000
b1001001 !
b1001001 %
b1000 )
b1000 (
b1000 '
1"
#456000
0"
#458000
b1001011 !
b1001011 %
b1000 )
b1000 (
b1000 '
1"
#460000
0"
#462000
b1001010 !
b1001010 %
b1000 )
b1000 (
b1000 '
1"
#464000
0"
#466000
b1001110 !
b1001110 %
b1000 )
b1000 (
b1000 '
1"
#468000
0"
#470000
b1001111 !
b1001111 %
b1000 )
b1000 (
b1000 '
1"
#472000
0"
#474000
b1001101 !
b1001101 %
b1000 )
b1000 (
b1000 '
1"
#476000
0"
#478000
b1001100 !
b1001100 %
b1000 )
b1000 (
b1000 '
1"
#480000
0"
#482000
b1000100 !
b1000100 %
b1000 )
b1000 (
b1000 '
1"
#484000
0"
#486000
b1000101 !
b1000101 %
b1000 )
b1000 (
b1000 '
1"
#488000
0"
#490000
b1000111 !
b1000111 %
b1000 )
b1000 (
b1000 '
1"
#492000
0"
#494000
b1000110 !
b1000110 %
b1000 )
b1000 (
b1000 '
1"
#496000
0"
#498000
b1000010 !
b1000010 %
b1000 )
b1000 (
b1000 '
1"
#500000
0"
#502000
b1000011 !
b1000011 %
b1000 )
b1000 (
b1000 '
1"
#504000
0"
#506000
b1000001 !
b1000001 %
b1000 )
b1000 (
b1000 '
1"
#508000
0"
#510000
b1000000 !
b1000000 %
b1000 )
b1000 (
b1000 '
1"
#512000
0"
#514000
b11000000 !
b11000000 %
b1000 )
b1000 (
b1000 '
1"
#516000
0"
#518000
b11000001 !
b11000001 %
b1000 )
b1000 (
b1000 '
1"
#520000
0"
#522000
b11000011 !
b11000011 %
b1000 )
b1000 (
b1000 '
1"
#524000
0"
#526000
b11000010 !
b11000010 %
b1000 )
b1000 (
b1000 '
1"
#528000
0"
#530000
b11000110 !
b11000110 %
b1000 )
b1000 (
b1000 '
1"
#532000
0"
#534000
b11000111 !
b11000111 %
b1000 )
b1000 (
b1000 '
1"
#536000
0"
#538000
b11000101 !
b11000101 %
b1000 )
b1000 (
b1000 '
1"
#540000
0"
#542000
b11000100 !
b11000100 %
b1000 )
b1000 (
b1000 '
1"
#544000
0"
#546000
b11001100 !
b11001100 %
b1000 )
b1000 (
b1000 '
1"
#548000
0"
#550000
b11001101 !
b11001101 %
b1000 )
b1000 (
b1000 '
1"
#552000
0"
#554000
b11001111 !
b11001111 %
b1000 )
b1000 (
b1000 '
1"
#556000
0"
#558000
b11001110 !
b11001110 %
b1000 )
b1000 (
b1000 '
1"
#560000
0"
#562000
b11001010 !
b11001010 %
b1000 )
b1000 (
b1000 '
1"
#564000
0"
#566000
b11001011 !
b11001011 %
b1000 )
b1000 (
b1000 '
1"
#568000
0"
#570000
b11001001 !
b11001001 %
b1000 )
b1000 (
b1000 '
1"
#572000
0"
#574000
b11001000 !
b11001000 %
b1000 )
b1000 (
b1000 '
1"
#576000
0"
#578000
b11011000 !
b11011000 %
b1000 )
b1000 (
b1000 '
1"
#580000
0"
#582000
b11011001 !
b11011001 %
b1000 )
b1000 (
b1000 '
1"
#584000
0"
#586000
b11011011 !
b11011011 %
b1000 )
b1000 (
b1000 '
1"
#588000
0"
#590000
b11011010 !
b11011010 %
b1000 )
b1000 (
b1000 '
1"
#592000
0"
#594000
b11011110 !
b11011110 %
b1000 )
b1000 (
b1000 '
1"
#596000
0"
#598000
b11011111 !
b11011111 %
b1000 )
b1000 (
b1000 '
1"
#600000
0"
#602000
b11011101 !
b11011101 %
b1000 )
b1000 (
b1000 '
1"
#604000
0"
#606000
b11011100 !
b11011100 %
b1000 )
b1000 (
b1000 '
1"
#608000
0"
#610000
b11010100 !
b11010100 %
b1000 )
b1000 (
b1000 '
1"
#612000
0"
#614000
b11010101 !
b11010101 %
b1000 )
b1000 (
b1000 '
1"
#616000
0"
#618000
b11010111 !
b11010111 %
b1000 )
b1000 (
b1000 '
1"
#620000
0"
#622000
b11010110 !
b11010110 %
b1000 )
b1000 (
b1000 '
1"
#624000
0"
#626000
b11010010 !
b11010010 %
b1000 )
b1000 (
b1000 '
1"
#628000
0"
#630000
b11010011 !
b11010011 %
b1000 )
b1000 (
b1000 '
1"
#632000
0"
#634000
b11010001 !
b11010001 %
b1000 )
b1000 (
b1000 '
1"
#636000
0"
#638000
b11010000 !
b11010000 %
b1000 )
b1000 (
b1000 '
1"
#640000
0"
#642000
b11110000 !
b11110000 %
b1000 )
b1000 (
b1000 '
1"
#644000
0"
#646000
b11110001 !
b11110001 %
b1000 )
b1000 (
b1000 '
1"
#648000
0"
#650000
b11110011 !
b11110011 %
b1000 )
b1000 (
b1000 '
1"
#652000
0"
#654000
b11110010 !
b11110010 %
b1000 )
b1000 (
b1000 '
1"
#656000
0"
#658000
b11110110 !
b11110110 %
b1000 )
b1000 (
b1000 '
1"
#660000
0"
#662000
b11110111 !
b11110111 %
b1000 )
b1000 (
b1000 '
1"
#664000
0"
#666000
b11110101 !
b11110101 %
b1000 )
b1000 (
b1000 '
1"
#668000
0"
#670000
b11110100 !
b11110100 %
b1000 )
b1000 (
b1000 '
1"
#672000
0"
#674000
b11111100 !
b11111100 %
b1000 )
b1000 (
b1000 '
1"
#676000
0"
#678000
b11111101 !
b11111101 %
b1000 )
b1000 (
b1000 '
1"
#680000
0"
#682000
b11111111 !
b11111111 %
b1000 )
b1000 (
b1000 '
1"
#684000
0"
#686000
b11111110 !
b11111110 %
b1000 )
b1000 (
b1000 '
1"
#688000
0"
#690000
b11111010 !
b11111010 %
b1000 )
b1000 (
b1000 '
1"
#692000
0"
#694000
b11111011 !
b11111011 %
b1000 )
b1000 (
b1000 '
1"
#696000
0"
#698000
b11111001 !
b11111001 %
b1000 )
b1000 (
b1000 '
1"
#700000
0"
#702000
b11111000 !
b11111000 %
b1000 )
b1000 (
b1000 '
1"
#704000
0"
#706000
b11101000 !
b11101000 %
b1000 )
b1000 (
b1000 '
1"
#708000
0"
#710000
b11101001 !
b11101001 %
b1000 )
b1000 (
b1000 '
1"
#712000
0"
#714000
b11101011 !
b11101011 %
b1000 )
b1000 (
b1000 '
1"
#716000
0"
#718000
b11101010 !
b11101010 %
b1000 )
b1000 (
b1000 '
1"
#720000
0"
#722000
b11101110 !
b11101110 %
b1000 )
b1000 (
b1000 '
1"
#724000
0"
#726000
b11101111 !
b11101111 %
b1000 )
b1000 (
b1000 '
1"
#728000
0"
#730000
b11101101 !
b11101101 %
b1000 )
b1000 (
b1000 '
1"
#732000
0"
#734000
b11101100 !
b11101100 %
b1000 )
b1000 (
b1000 '
1"
#736000
0"
#738000
b11100100 !
b11100100 %
b1000 )
b1000 (
b1000 '
1"
#740000
0"
#742000
b11100101 !
b11100101 %
b1000 )
b1000 (
b1000 '
1"
#744000
0"
#746000
b11100111 !
b11100111 %
b1000 )
b1000 (
b1000 '
1"
#748000
0"
#750000
b11100110 !
b11100110 %
b1000 )
b1000 (
b1000 '
1"
#752000
0"
#754000
b11100010 !
b11100010 %
b1000 )
b1000 (
b1000 '
1"
#756000
0"
#758000
b11100011 !
b11100011 %
b1000 )
b1000 (
b1000 '
1"
#760000
0"
#762000
b11100001 !
b11100001 %
b1000 )
b1000 (
b1000 '
1"
#764000
0"
#766000
b11100000 !
b11100000 %
b1000 )
b1000 (
b1000 '
1"
#768000
0"
#770000
b10100000 !
b10100000 %
b1000 )
b1000 (
b1000 '
1"
#772000
0"
#774000
b10100001 !
b10100001 %
b1000 )
b1000 (
b1000 '
1"
#776000
0"
#778000
b10100011 !
b10100011 %
b1000 )
b1000 (
b1000 '
1"
#780000
0"
#782000
b10100010 !
b10100010 %
b1000 )
b1000 (
b1000 '
1"
#784000
0"
#786000
b10100110 !
b10100110 %
b1000 )
b1000 (
b1000 '
1"
#788000
0"
#790000
b10100111 !
b10100111 %
b1000 )
b1000 (
b1000 '
1"
#792000
0"
#794000
b10100101 !
b10100101 %
b1000 )
b1000 (
b1000 '
1"
#796000
0"
#798000
b10100100 !
b10100100 %
b1000 )
b1000 (
b1000 '
1"
#800000
0"
#802000
b10101100 !
b10101100 %
b1000 )
b1000 (
b1000 '
1"
#804000
0"
#806000
b10101101 !
b10101101 %
b1000 )
b1000 (
b1000 '
1"
#808000
0"
#810000
b10101111 !
b10101111 %
b1000 )
b1000 (
b1000 '
1"
#812000
0"
#814000
b10101110 !
b10101110 %
b1000 )
b1000 (
b1000 '
1"
#816000
0"
#818000
b10101010 !
b10101010 %
b1000 )
b1000 (
b1000 '
1"
#820000
0"
#822000
b10101011 !
b10101011 %
b1000 )
b1000 (
b1000 '
1"
#824000
0"
#826000
b10101001 !
b10101001 %
b1000 )
b1000 (
b1000 '
1"
#828000
0"
#830000
b10101000 !
b10101000 %
b1000 )
b1000 (
b1000 '
1"
#832000
0"
#834000
b10111000 !
b10111000 %
b1000 )
b1000 (
b1000 '
1"
#836000
0"
#838000
b10111001 !
b10111001 %
b1000 )
b1000 (
b1000 '
1"
#840000
0"
#842000
b10111011 !
b10111011 %
b1000 )
b1000 (
b1000 '
1"
#844000
0"
#846000
b10111010 !
b10111010 %
b1000 )
b1000 (
b1000 '
1"
#848000
0"
#850000
b10111110 !
b10111110 %
b1000 )
b1000 (
b1000 '
1"
#852000
0"
#854000
b10111111 !
b10111111 %
b1000 )
b1000 (
b1000 '
1"
#856000
0"
#858000
b10111101 !
b10111101 %
b1000 )
b1000 (
b1000 '
1"
#860000
0"
#862000
b10111100 !
b10111100 %
b1000 )
b1000 (
b1000 '
1"
#864000
0"
#866000
b10110100 !
b10110100 %
b1000 )
b1000 (
b1000 '
1"
#868000
0"
#870000
b10110101 !
b10110101 %
b1000 )
b1000 (
b1000 '
1"
#872000
0"
#874000
b10110111 !
b10110111 %
b1000 )
b1000 (
b1000 '
1"
#876000
0"
#878000
b10110110 !
b10110110 %
b1000 )
b1000 (
b1000 '
1"
#880000
0"
#882000
b10110010 !
b10110010 %
b1000 )
b1000 (
b1000 '
1"
#884000
0"
#886000
b10110011 !
b10110011 %
b1000 )
b1000 (
b1000 '
1"
#888000
0"
#890000
b10110001 !
b10110001 %
b1000 )
b1000 (
b1000 '
1"
#892000
0"
#894000
b10110000 !
b10110000 %
b1000 )
b1000 (
b1000 '
1"
#896000
0"
#898000
b10010000 !
b10010000 %
b1000 )
b1000 (
b1000 '
1"
#900000
0"
#902000
b10010001 !
b10010001 %
b1000 )
b1000 (
b1000 '
1"
#904000
0"
#906000
b10010011 !
b10010011 %
b1000 )
b1000 (
b1000 '
1"
#908000
0"
#910000
b10010010 !
b10010010 %
b1000 )
b1000 (
b1000 '
1"
#912000
0"
#914000
b10010110 !
b10010110 %
b1000 )
b1000 (
b1000 '
1"
#916000
0"
#918000
b10010111 !
b10010111 %
b1000 )
b1000 (
b1000 '
1"
#920000
0"
#922000
b10010101 !
b10010101 %
b1000 )
b1000 (
b1000 '
1"
#924000
0"
#926000
b10010100 !
b10010100 %
b1000 )
b1000 (
b1000 '
1"
#928000
0"
#930000
b10011100 !
b10011100 %
b1000 )
b1000 (
b1000 '
1"
#932000
0"
#934000
b10011101 !
b10011101 %
b1000 )
b1000 (
b1000 '
1"
#936000
0"
#938000
b10011111 !
b10011111 %
b1000 )
b1000 (
b1000 '
1"
#940000
0"
#942000
b10011110 !
b10011110 %
b1000 )
b1000 (
b1000 '
1"
#944000
0"
#946000
b10011010 !
b10011010 %
b1000 )
b1000 (
b1000 '
1"
#948000
0"
#950000
b10011011 !
b10011011 %
b1000 )
b1000 (
b1000 '
1"
#952000
0"
#954000
b10011001 !
b10011001 %
b1000 )
b1000 (
b1000 '
1"
#956000
0"
#958000
b10011000 !
b10011000 %
b1000 )
b1000 (
b1000 '
1"
#960000
0"
#962000
b10001000 !
b10001000 %
b1000 )
b1000 (
b1000 '
1"
#964000
0"
#966000
b10001001 !
b10001001 %
b1000 )
b1000 (
b1000 '
1"
#968000
0"
#970000
b10001011 !
b10001011 %
b1000 )
b1000 (
b1000 '
1"
#972000
0"
#974000
b10001010 !
b10001010 %
b1000 )
b1000 (
b1000 '
1"
#976000
0"
#978000
b10001110 !
b10001110 %
b1000 )
b1000 (
b1000 '
1"
#980000
0"
#982000
b10001111 !
b10001111 %
b1000 )
b1000 (
b1000 '
1"
#984000
0"
#986000
b10001101 !
b10001101 %
b1000 )
b1000 (
b1000 '
1"
#988000
0"
#990000
b10001100 !
b10001100 %
b1000 )
b1000 (
b1000 '
1"
#992000
0"
#994000
b10000100 !
b10000100 %
b1000 )
b1000 (
b1000 '
1"
#996000
0"
#998000
b10000101 !
b10000101 %
b1000 )
b1000 (
b1000 '
1"
#1000000
0"
#1002000
b10000111 !
b10000111 %
b1000 )
b1000 (
b1000 '
1"
#1004000
0"
#1006000
b10000110 !
b10000110 %
b1000 )
b1000 (
b1000 '
1"
#1008000
0"
#1010000
b10000010 !
b10000010 %
b1000 )
b1000 (
b1000 '
1"
#1012000
0"
#1014000
b10000011 !
b10000011 %
b1000 )
b1000 (
b1000 '
1"
#1016000
0"
#1018000
b10000001 !
b10000001 %
b1000 )
b1000 (
b1000 '
1"
#1020000
0"
#1022000
b10000000 !
b10000000 %
b1000 )
b1000 (
b1000 '
1"
#1024000
0"
#1026000
b0 !
b0 %
b1000 )
0&
b1000 (
b1000 '
1"
#1028000
0"
#1030000
b1 !
b1 %
b1000 )
b1000 (
b1000 '
1"
#1032000
0"
#1034000
b11 !
b11 %
b1000 )
b1000 (
b1000 '
1"
#1036000
0"
#1038000
b10 !
b10 %
b1000 )
b1000 (
b1000 '
1"
#1040000
0"
#1042000
b110 !
b110 %
b1000 )
b1000 (
b1000 '
1"
#1044000
0"
#1046000
b111 !
b111 %
b1000 )
b1000 (
b1000 '
1"
#1048000
0"
#1050000
b101 !
b101 %
b1000 )
b1000 (
b1000 '
1"
#1052000
0"
#1054000
b100 !
b100 %
b1000 )
b1000 (
b1000 '
1"
#1056000
0"
#1058000
b1100 !
b1100 %
b1000 )
b1000 (
b1000 '
1"
#1060000
0"
#1062000
b1101 !
b1101 %
b1000 )
b1000 (
b1000 '
1"
#1064000
0"
#1066000
b1111 !
b1111 %
b1000 )
b1000 (
b1000 '
1"
#1068000
0"
#1070000
b1110 !
b1110 %
b1000 )
b1000 (
b1000 '
1"
#1072000
0"
#1074000
b1010 !
b1010 %
b1000 )
b1000 (
b1000 '
1"
#1076000
0"
#1078000
b1011 !
b1011 %
b1000 )
b1000 (
b1000 '
1"
#1080000
0"
#1082000
b1001 !
b1001 %
b1000 )
b1000 (
b1000 '
1"
#1084000
0"
#1086000
b1000 !
b1000 %
b1000 )
b1000 (
b1000 '
1"
#1088000
0"
#1090000
b11000 !
b11000 %
b1000 )
b1000 (
b1000 '
1"
#1092000
0"
#1094000
b11001 !
b11001 %
b1000 )
b1000 (
b1000 '
1"
#1096000
0"
#1098000
b11011 !
b11011 %
b1000 )
b1000 (
b1000 '
1"
#1100000
0"
#1102000
b11010 !
b11010 %
b1000 )
b1000 (
b1000 '
1"
#1104000
0"
#1106000
b11110 !
b11110 %
b1000 )
b1000 (
b1000 '
1"
#1108000
0"
#1110000
b11111 !
b11111 %
b1000 )
b1000 (
b1000 '
1"
#1112000
0"
#1114000
b11101 !
b11101 %
b1000 )
b1000 (
b1000 '
1"
#1116000
0"
#1118000
b11100 !
b11100 %
b1000 )
b1000 (
b1000 '
1"
#1120000
0"
#1122000
b10100 !
b10100 %
b1000 )
b1000 (
b1000 '
1"
#1124000
0"
#1126000
b10101 !
b10101 %
b1000 )
b1000 (
b1000 '
1"
#1128000
0"
#1130000
b10111 !
b10111 %
b1000 )
b1000 (
b1000 '
1"
#1132000
0"
#1134000
b10110 !
b10110 %
b1000 )
b1000 (
b1000 '
1"
#1136000
0"
#1138000
b10010 !
b10010 %
b1000 )
b1000 (
b1000 '
1"
#1140000
0"
#1142000
b10011 !
b10011 %
b1000 )
b1000 (
b1000 '
1"
#1144000
0"
#1146000
b10001 !
b10001 %
b1000 )
b1000 (
b1000 '
1"
#1148000
0"
#1150000
b10000 !
b10000 %
b1000 )
b1000 (
b1000 '
1"
#1152000
0"
#1154000
b110000 !
b110000 %
b1000 )
b1000 (
b1000 '
1"
#1156000
0"
#1158000
b110001 !
b110001 %
b1000 )
b1000 (
b1000 '
1"
#1160000
0"
#1162000
b110011 !
b110011 %
b1000 )
b1000 (
b1000 '
1"
#1164000
0"
#1166000
b110010 !
b110010 %
b1000 )
b1000 (
b1000 '
1"
#1168000
0"
#1170000
b110110 !
b110110 %
b1000 )
b1000 (
b1000 '
1"
#1172000
0"
#1174000
b110111 !
b110111 %
b1000 )
b1000 (
b1000 '
1"
#1176000
0"
#1178000
b110101 !
b110101 %
b1000 )
b1000 (
b1000 '
1"
#1180000
0"
#1182000
b110100 !
b110100 %
b1000 )
b1000 (
b1000 '
1"
#1184000
0"
#1186000
b111100 !
b111100 %
b1000 )
b1000 (
b1000 '
1"
#1188000
0"
#1190000
b111101 !
b111101 %
b1000 )
b1000 (
b1000 '
1"
#1192000
0"
#1194000
b111111 !
b111111 %
b1000 )
b1000 (
b1000 '
1"
